LICENSE
MANIFEST.in
README.rst
pyproject.toml
setup.cfg
setup.py
crud_framework/__init__.py
crud_framework/admin.py
crud_framework/apps.py
crud_framework/errors.py
crud_framework/tests.py
crud_framework/migrations/__init__.py
crud_framework/models/__init__.py
crud_framework/models/base.py
crud_framework/models/safe_delete.py
crud_framework/schemas/__init__.py
crud_framework/schemas/base.py
crud_framework/schemas/functional.py
crud_framework/schemas/lookups.py
crud_framework/schemas/modular.py
crud_framework/schemas/user_aware.py
crud_framework/views/__init__.py
crud_framework/views/base.py
crud_framework/views/functional.py
crud_framework/views/lookups.py
crud_framework/views/modular.py
crud_framework/views/oauth.py
djangoCRUDframework.egg-info/PKG-INFO
djangoCRUDframework.egg-info/SOURCES.txt
djangoCRUDframework.egg-info/dependency_links.txt
djangoCRUDframework.egg-info/requires.txt
djangoCRUDframework.egg-info/top_level.txt