Metadata-Version: 2.1
Name: djangoCRUDframework
Version: 0.3.5
Summary: A Django app implementing basic CRUD and more!
Home-page: https://github.com/amerepos/DjangoCRUD
Author: Ahmad Amer
Author-email: ahmad.tarek.amer@gmail.com
License: mit
Platform: UNKNOWN
Classifier: Environment :: Web Environment
Classifier: Framework :: Django
Classifier: Framework :: Django :: 3.2
Classifier: Intended Audience :: Developers
Classifier: License :: OSI Approved :: BSD License
Classifier: Operating System :: OS Independent
Classifier: Programming Language :: Python
Classifier: Programming Language :: Python :: 3
Classifier: Programming Language :: Python :: 3 :: Only
Classifier: Programming Language :: Python :: 3.8
Classifier: Programming Language :: Python :: 3.9
Classifier: Topic :: Internet :: WWW/HTTP
Classifier: Topic :: Internet :: WWW/HTTP :: Dynamic Content
Requires-Python: >=3.0
License-File: LICENSE
